owo/__init__.py
text_to_owo-2.0.1.dist-info/LICENSE
text_to_owo-2.0.1.dist-info/METADATA
text_to_owo-2.0.1.dist-info/WHEEL
text_to_owo-2.0.1.dist-info/top_level.txt
text_to_owo-2.0.1.dist-info/RECORD
